path2insight/__init__.py
path2insight/collect.py
path2insight/core.py
path2insight/decorators.py
path2insight/handling.py
path2insight/parse.py
path2insight/utils.py
path2insight/algorithms/__init__.py
path2insight/algorithms/stringdist.py
path2insight/datasets/__init__.py
path2insight/datasets/external.py
path2insight/datasets/data/ensembl90.csv.gzip
path2insight/datasets/data/pride.csv.gzip
path2insight/datasets/extensions/__init__.py
path2insight/explore/__init__.py
path2insight/explore/distance.py
path2insight/explore/metrics.py
path2insight/explore/stats.py
path2insight/explore/tagger.py
path2insight/external/__init__.py
path2insight/external/nltk.py
path2insight/tests/__init__.py
path2insight/tests/test_core.py
path2insight/tests/test_datasets.py
path2insight/tests/test_handling.py
path2insight/tests/test_ngrams.py
path2insight/tests/test_parse.py
path2insight/tests/test_tagger.py
path2insight/tokenizers/__init__.py
path2insight/tokenizers/tokenizers.py
path2insight-1.0b2.dist-info/DESCRIPTION.rst
path2insight-1.0b2.dist-info/LICENSE.txt
path2insight-1.0b2.dist-info/METADATA
path2insight-1.0b2.dist-info/RECORD
path2insight-1.0b2.dist-info/WHEEL
path2insight-1.0b2.dist-info/metadata.json
path2insight-1.0b2.dist-info/top_level.txt
