Metadata-Version: 2.0
Name: path2insight
Version: 1.0b2
Summary: A set of tools to retrieve information from filepaths.
Home-page: https://github.com/armell/path2insight
Author: Armel Lefebvre, Jonathan de Bruin
Author-email: A.E.J.Lefebvre@uu.nl, j.debruin1@uu.nl
License: MIT
Keywords: filepath pathlib datamanagement exploration
Platform: UNKNOWN
Classifier: Development Status :: 4 - Beta
Classifier: Intended Audience :: Developers
Classifier: Topic :: Software Development :: Build Tools
Classifier: License :: OSI Approved :: MIT License
Classifier: Programming Language :: Python :: 2
Classifier: Programming Language :: Python :: 2.7
Classifier: Programming Language :: Python :: 3
Classifier: Programming Language :: Python :: 3.3
Classifier: Programming Language :: Python :: 3.4
Classifier: Programming Language :: Python :: 3.5
Classifier: Programming Language :: Python :: 3.6
Provides-Extra: test
Requires-Dist: parameterized; extra == 'test'
Requires-Dist: pytest; extra == 'test'
